lab2/tx.v
module tx(
    input wire clk_100mhz,
    input wire rst,
    input wire start,
    input wire [7:0] data,

    output reg tx_line
    );

    // localparam  countMax = 100000000/9600; // 100MHz / 9600 baudrate
    localparam countMax = 2; // for testing 
    reg [25:0] count = 0;
    parameter S0 = 4'd0, S1 = 4'd1, S2 = 4'd2, S3 = 4'd3, S4 = 4'd4, S5 = 4'd5, S6 = 4'd6, S7 = 4'd7, S8 = 4'd8, S9 = 4'd9;
    reg [3:0] currentState;
    reg [3:0] nextState;
    reg[7:0] data_reg;
    reg start_reg;

    //= state transistion =//
    always @(*)begin
        case(currentState)
            S0: begin
                if(start_reg)
                    nextState = S1;
                else
                    nextState = S0;
            end
            S1: begin
                nextState = S2;
            end
            S2: begin
                nextState = S3;
            end
            S3: begin
                nextState = S4;
            end
            S4: begin
                nextState = S5;
            end
            S5: begin
                nextState = S6;
            end
            S6: begin
                nextState = S7;
            end
            S7: begin             
                nextState = S8;
            end
            S8: begin
                nextState = S9;
            end
            S9: begin
                nextState = S0;
            end
            default: nextState = S0;
        endcase
    end

    //= output update =//
    always @(posedge clk_100mhz or posedge rst)begin
        if(rst) begin
            currentState <= S0;
            tx_line <= 1'b1;
            count <= 0;
            start_reg <= 1'b0;
        end else if (count < countMax) begin
            count <= count + 1;

            if(start && currentState == S0 && !start_reg)
                start_reg <= 1'b1;
        end
        else begin
            count <= 0;
            currentState <= nextState;
            case(currentState)
                S0: begin
                    tx_line <= 1'b1;
                    start_reg <= 1'b0;
                end
                S1: begin
                    tx_line <= 1'b0;
                    data_reg <= data;
                end
                S2: tx_line <= data_reg[0];
                S3: tx_line <= data_reg[1];
                S4: tx_line <= data_reg[2];
                S5: tx_line <= data_reg[3];
                S6: tx_line <= data_reg[4];
                S7: tx_line <= data_reg[5];
                S8: tx_line <= data_reg[6];
                S9: tx_line <= data_reg[7];
                default: tx_line <= 1'b1;
            endcase
        end
    end
endmodule

lab2/testbench/tx_tb.v
`timescale 1ns / 1ps

module tx_tb();

reg clk;
reg rst;
reg start;
reg [7:0] data;
wire tx_line;

reg correct;
integer testNum;

// Instantiate TX
tx my_tx(
    .clk_100mhz(clk),
    .rst(rst),
    .start(start),
    .data(data),
    .tx_line(tx_line)
);

// Clock generation
// countMax = 2 for testing, so period is 4 cycles
always begin
    #0.5 clk = ~clk; 
end

initial begin
    $dumpfile("wave.vcd");
    $dumpvars(0, tx_tb);
    clk = 0;
    rst = 0;
    start = 0;
    data = 8'b10101010;
    correct = 1;

    // reset check
    testNum = 1;
    start = 1;
    #1.5;
    start = 0;
    #3;
    rst = 1;
    #3;
    rst = 0;

    if (tx_line != 1) correct = 0;

    // regular transmission check 1
    correct = 1;
    testNum = 2;
    #3;
    start = 1;
    #6.01;
    start = 0;
    if(tx_line != 0) correct = 0;
    #2;
    correct = 1;
    if(tx_line != data[0]) correct = 0;
    testNum = 3;
    #3;
    correct = 1;
    if(tx_line != data[1]) correct = 0;
    testNum = 4;
    #3;
    correct = 1;
    if(tx_line != data[2]) correct = 0;
    testNum = 5;
    #3;
    correct = 1;
    if(tx_line != data[3]) correct = 0;
    testNum = 6;
    #3;
    correct = 1;
    if(tx_line != data[4]) correct = 0;
    testNum = 7;
    #3;
    correct = 1;
    if(tx_line != data[5]) correct = 0;
    testNum = 8;
    #3;
    correct = 1;
    if(tx_line != data[6]) correct = 0;
    testNum = 9;
    #3;
    correct = 1;
    if(tx_line != data[7]) correct = 0;
    testNum = 10;
    #3;
    correct = 1;
    if(tx_line != 1) correct = 0;
    testNum = 11;

    // change in data between transmission should not affect current transmission
    #3;
    testNum = 12;
    rst = 1;
    #1;
    rst = 0;
    #3;
    correct = 1;
    if (tx_line != 1) correct = 0;
    #3;
    start = 1;
    #6;
    start = 0;
    correct = 1;
    if(tx_line != 0) correct = 0;
    #3;
    correct = 1;
    if(tx_line != data[0]) correct = 0;
    testNum = 13;
    #3;
    correct = 1;
    if(tx_line != data[1]) correct = 0;
    testNum = 14;
    #3;
    correct = 1;
    if(tx_line != data[2]) correct = 0;
    testNum = 15;
    data = ~data; // change data to make sure it is latched in at the beginning of transmission, not updated in the middle
    #3;
    correct = 1;
    if(tx_line != ~data[3]) correct = 0;
    testNum = 16;
    #3;
    correct = 1;
    if(tx_line != ~data[4]) correct = 0;
    testNum = 17;
    #3;
    correct = 1;
    if(tx_line != ~data[5]) correct = 0;
    testNum = 18;
    #3;
    correct = 1;
    if(tx_line != ~data[6]) correct = 0;
    testNum = 19;
    #3;
    correct = 1;
    if(tx_line != ~data[7]) correct = 0;
    testNum = 20;
    #3;
    correct = 1;
    if(tx_line != 1) correct = 0;
    testNum = 21;

    // check another regular transmission 
    data = 8'b01010101;
    testNum = 22;
    correct = 1;
    if (tx_line != 1) correct = 0;
    #3;
    start = 1;
    #6;
    start = 0;
    correct = 1;
    if(tx_line != 0) correct = 0;
    #3;
    correct = 1;
    if(tx_line != data[0]) correct = 0;
    testNum = 23;
    #3;
    correct = 1;
    if(tx_line != data[1]) correct = 0;
    testNum = 24;
    #3;
    correct = 1;
    if(tx_line != data[2]) correct = 0;
    testNum = 25;
    data = data; 
    #3;
    correct = 1;
    if(tx_line != data[3]) correct = 0;
    testNum = 26;
    #3;
    correct = 1;
    if(tx_line != data[4]) correct = 0;
    testNum = 27;
    #3;
    correct = 1;
    if(tx_line != data[5]) correct = 0;
    testNum = 28;
    #3;
    correct = 1;
    if(tx_line != data[6]) correct = 0;
    testNum = 29;
    #3;
    correct = 1;
    if(tx_line != data[7]) correct = 0;
    testNum = 30;
    #3;
    correct = 1;
    if(tx_line != 1) correct = 0;
    testNum = 31;

    // check reset between transmission
    data = 8'b00100101;
    testNum = 32;
    correct = 1;
    if (tx_line != 1) correct = 0;
    #3;
    start = 1;
    #6;
    start = 0;
    correct = 1;
    if(tx_line != 0) correct = 0;
    #3;
    correct = 1;
    if(tx_line != data[0]) correct = 0;
    testNum = 33;
    #3;
    correct = 1;
    if(tx_line != data[1]) correct = 0;
    testNum = 34;
    #3;
    correct = 1;
    if(tx_line != data[2]) correct = 0;
    testNum = 35;
    data = data; 
    #3;
    correct = 1;
    if(tx_line != data[3]) correct = 0;
    testNum = 36;
    rst = 1;
    #3;
    rst = 0;
    correct = 1;
    if(tx_line != 1'b1) correct = 0;
    testNum = 37;
    #3;
    correct = 1;
    if(tx_line != 1'b1) correct = 0;
    testNum = 38;
    #3;
    correct = 1;
    if(tx_line != 1'b1) correct = 0;
    testNum = 39;
    #3;
    correct = 1;
    if(tx_line != 1'b1) correct = 0;
    testNum = 40;
    #3;
    correct = 1;
    if(tx_line != 1'b1) correct = 0;
    testNum = 41;


    // Finish
    #5;
    $stop;
end

endmodule

lab2/waveforms/tx_wave.vcd
$date
	Thu Apr  9 18:25:19 2026
$end
$version
	Icarus Verilog
$end
$timescale
	1ps
$end
$scope module tx_tb $end
$var wire 1 ! tx_line $end
$var reg 1 " clk $end
$var reg 1 # correct $end
$var reg 8 $ data [7:0] $end
$var reg 1 % rst $end
$var reg 1 & start $end
$var integer 32 ' testNum [31:0] $end
$scope module my_tx $end
$var wire 1 " clk_100mhz $end
$var wire 8 ( data [7:0] $end
$var wire 1 % rst $end
$var wire 1 & start $end
$var parameter 4 ) S0 $end
$var parameter 4 * S1 $end
$var parameter 4 + S2 $end
$var parameter 4 , S3 $end
$var parameter 4 - S4 $end
$var parameter 4 . S5 $end
$var parameter 4 / S6 $end
$var parameter 4 0 S7 $end
$var parameter 4 1 S8 $end
$var parameter 4 2 S9 $end
$var parameter 32 3 countMax $end
$var reg 26 4 count [25:0] $end
$var reg 4 5 currentState [3:0] $end
$var reg 8 6 data_reg [7:0] $end
$var reg 4 7 nextState [3:0] $end
$var reg 1 8 start_reg $end
$var reg 1 ! tx_line $end
$upscope $end
$upscope $end
$enddefinitions $end
$comment Show the parameter values. $end
$dumpall
b10 3
b1001 2
b1000 1
b111 0
b110 /
b101 .
b100 -
b11 ,
b10 +
b1 *
b0 )
$end
#0
$dumpvars
x8
bx 7
bx 6
bx 5
b0 4
b10101010 (
b1 '
1&
0%
b10101010 $
1#
0"
x!
$end
#500
b1 4
1"
#1000
0"
#1500
b10 4
1"
0&
#2000
0"
#2500
1!
b0 4
1"
#3000
0"
#3500
b1 4
1"
#4000
0"
#4500
b0 7
08
b0 4
b0 5
1"
1%
#5000
0"
#5500
1"
#6000
0"
#6500
1"
#7000
0"
#7500
b1 4
1"
b10 '
0%
#8000
0"
#8500
b10 4
1"
#9000
0"
#9500
b0 4
1"
#10000
0"
#10500
b1 7
18
b1 4
1"
1&
#11000
0"
#11500
b10 4
1"
#12000
0"
#12500
b10 7
08
b1 5
b0 4
1"
#13000
0"
#13500
b1 4
1"
#14000
0"
#14500
b10 4
1"
#15000
0"
#15500
b11 7
b10101010 6
0!
b10 5
b0 4
1"
#16000
0"
#16500
b1 4
1"
#16510
0&
#17000
0"
#17500
b10 4
1"
#18000
0"
#18500
b100 7
b11 5
b0 4
1"
#18510
b11 '
#19000
0"
#19500
b1 4
1"
#20000
0"
#20500
b10 4
1"
#21000
0"
#21500
b101 7
1!
b100 5
b0 4
1"
#21510
b100 '
#22000
0"
#22500
b1 4
1"
#23000
0"
#23500
b10 4
1"
#24000
0"
#24500
b110 7
0!
b101 5
b0 4
1"
#24510
b101 '
#25000
0"
#25500
b1 4
1"
#26000
0"
#26500
b10 4
1"
#27000
0"
#27500
b111 7
1!
b110 5
b0 4
1"
#27510
b110 '
#28000
0"
#28500
b1 4
1"
#29000
0"
#29500
b10 4
1"
#30000
0"
#30500
b1000 7
0!
b111 5
b0 4
1"
#30510
b111 '
#31000
0"
#31500
b1 4
1"
#32000
0"
#32500
b10 4
1"
#33000
0"
#33500
b1001 7
1!
b1000 5
b0 4
1"
#33510
b1000 '
#34000
0"
#34500
b1 4
1"
#35000
0"
#35500
b10 4
1"
#36000
0"
#36500
b0 7
0!
b1001 5
b0 4
1"
#36510
b1001 '
#37000
0"
#37500
b1 4
1"
#38000
0"
#38500
b10 4
1"
#39000
0"
#39500
1!
b0 5
b0 4
1"
#39510
b1010 '
#40000
0"
#40500
b1 4
1"
#41000
0"
#41500
b10 4
1"
#42000
0"
#42500
b0 4
1"
#42510
b1011 '
#43000
0"
#43500
b1 4
1"
#44000
0"
#44500
b10 4
1"
#45000
0"
#45500
b0 4
1"
#45510
1%
b1100 '
#46000
0"
#46500
1"
#46510
0%
#47000
0"
#47500
b1 4
1"
#48000
0"
#48500
b10 4
1"
#49000
0"
#49500
b0 4
1"
#50000
0"
#50500
b1 4
1"
#51000
0"
#51500
b10 4
1"
#52000
0"
#52500
b0 4
1"
#52510
1&
#53000
0"
#53500
b1 7
18
b1 4
1"
#54000
0"
#54500
b10 4
1"
#55000
0"
#55500
b10 7
08
b1 5
b0 4
1"
#56000
0"
#56500
b1 4
1"
#57000
0"
#57500
b10 4
1"
#58000
0"
#58500
b11 7
0!
b10 5
b0 4
1"
#58510
0&
#59000
0"
#59500
b1 4
1"
#60000
0"
#60500
b10 4
1"
#61000
0"
#61500
b100 7
b11 5
b0 4
1"
#61510
b1101 '
#62000
0"
#62500
b1 4
1"
#63000
0"
#63500
b10 4
1"
#64000
0"
#64500
b101 7
1!
b100 5
b0 4
1"
#64510
b1110 '
#65000
0"
#65500
b1 4
1"
#66000
0"
#66500
b10 4
1"
#67000
0"
#67500
b110 7
0!
b101 5
b0 4
1"
#67510
b1010101 $
b1010101 (
b1111 '
#68000
0"
#68500
b1 4
1"
#69000
0"
#69500
b10 4
1"
#70000
0"
#70500
b111 7
1!
b110 5
b0 4
1"
#70510
b10000 '
#71000
0"
#71500
b1 4
1"
#72000
0"
#72500
b10 4
1"
#73000
0"
#73500
b1000 7
0!
b111 5
b0 4
1"
#73510
b10001 '
#74000
0"
#74500
b1 4
1"
#75000
0"
#75500
b10 4
1"
#76000
0"
#76500
b1001 7
1!
b1000 5
b0 4
1"
#76510
b10010 '
#77000
0"
#77500
b1 4
1"
#78000
0"
#78500
b10 4
1"
#79000
0"
#79500
b0 7
0!
b1001 5
b0 4
1"
#79510
b10011 '
#80000
0"
#80500
b1 4
1"
#81000
0"
#81500
b10 4
1"
#82000
0"
#82500
1!
b0 5
b0 4
1"
#82510
b10100 '
#83000
0"
#83500
b1 4
1"
#84000
0"
#84500
b10 4
1"
#85000
0"
#85500
b0 4
1"
#85510
b10110 '
#86000
0"
#86500
b1 4
1"
#87000
0"
#87500
b10 4
1"
#88000
0"
#88500
b0 4
1"
#88510
1&
#89000
0"
#89500
b1 7
18
b1 4
1"
#90000
0"
#90500
b10 4
1"
#91000
0"
#91500
b10 7
08
b1 5
b0 4
1"
#92000
0"
#92500
b1 4
1"
#93000
0"
#93500
b10 4
1"
#94000
0"
#94500
b11 7
b1010101 6
0!
b10 5
b0 4
1"
#94510
0&
#95000
0"
#95500
b1 4
1"
#96000
0"
#96500
b10 4
1"
#97000
0"
#97500
b100 7
1!
b11 5
b0 4
1"
#97510
b10111 '
#98000
0"
#98500
b1 4
1"
#99000
0"
#99500
b10 4
1"
#100000
0"
#100500
b101 7
0!
b100 5
b0 4
1"
#100510
b11000 '
#101000
0"
#101500
b1 4
1"
#102000
0"
#102500
b10 4
1"
#103000
0"
#103500
b110 7
1!
b101 5
b0 4
1"
#103510
b11001 '
#104000
0"
#104500
b1 4
1"
#105000
0"
#105500
b10 4
1"
#106000
0"
#106500
b111 7
0!
b110 5
b0 4
1"
#106510
b11010 '
#107000
0"
#107500
b1 4
1"
#108000
0"
#108500
b10 4
1"
#109000
0"
#109500
b1000 7
1!
b111 5
b0 4
1"
#109510
b11011 '
#110000
0"
#110500
b1 4
1"
#111000
0"
#111500
b10 4
1"
#112000
0"
#112500
b1001 7
0!
b1000 5
b0 4
1"
#112510
b11100 '
#113000
0"
#113500
b1 4
1"
#114000
0"
#114500
b10 4
1"
#115000
0"
#115500
b0 7
1!
b1001 5
b0 4
1"
#115510
b11101 '
#116000
0"
#116500
b1 4
1"
#117000
0"
#117500
b10 4
1"
#118000
0"
#118500
0!
b0 5
b0 4
1"
#118510
b11110 '
#119000
0"
#119500
b1 4
1"
#120000
0"
#120500
b10 4
1"
#121000
0"
#121500
1!
b0 4
1"
#121510
b100101 $
b100101 (
b100000 '
#122000
0"
#122500
b1 4
1"
#123000
0"
#123500
b10 4
1"
#124000
0"
#124500
b0 4
1"
#124510
1&
#125000
0"
#125500
b1 7
18
b1 4
1"
#126000
0"
#126500
b10 4
1"
#127000
0"
#127500
b10 7
08
b1 5
b0 4
1"
#128000
0"
#128500
b1 4
1"
#129000
0"
#129500
b10 4
1"
#130000
0"
#130500
b11 7
b100101 6
0!
b10 5
b0 4
1"
#130510
0&
#131000
0"
#131500
b1 4
1"
#132000
0"
#132500
b10 4
1"
#133000
0"
#133500
b100 7
1!
b11 5
b0 4
1"
#133510
b100001 '
#134000
0"
#134500
b1 4
1"
#135000
0"
#135500
b10 4
1"
#136000
0"
#136500
b101 7
0!
b100 5
b0 4
1"
#136510
b100010 '
#137000
0"
#137500
b1 4
1"
#138000
0"
#138500
b10 4
1"
#139000
0"
#139500
b110 7
1!
b101 5
b0 4
1"
#139510
b100011 '
#140000
0"
#140500
b1 4
1"
#141000
0"
#141500
b10 4
1"
#142000
0"
#142500
b111 7
0!
b110 5
b0 4
1"
#142510
b0 7
1!
b0 5
1%
b100100 '
#143000
0"
#143500
1"
#144000
0"
#144500
1"
#145000
0"
#145500
1"
#145510
b100101 '
0%
#146000
0"
#146500
b1 4
1"
#147000
0"
#147500
b10 4
1"
#148000
0"
#148500
b0 4
1"
#148510
b100110 '
#149000
0"
#149500
b1 4
1"
#150000
0"
#150500
b10 4
1"
#151000
0"
#151500
b0 4
1"
#151510
b100111 '
#152000
0"
#152500
b1 4
1"
#153000
0"
#153500
b10 4
1"
#154000
0"
#154500
b0 4
1"
#154510
b101000 '
#155000
0"
#155500
b1 4
1"
#156000
0"
#156500
b10 4
1"
#157000
0"
#157500
b0 4
1"
#157510
b101001 '
#158000
0"
#158500
b1 4
1"
#159000
0"
#159500
b10 4
1"
#160000
0"
#160500
b0 4
1"
#161000
0"
#161500
b1 4
1"
#162000
0"
#162500
b10 4
1"
