lab2/rx.v
module rx(
    input wire clk_100mhz,
    input wire rst,
    input wire rx_line,

    output reg [7:0] data
    );

    // localparam  countMax = 100000000/9600; // 100MHz / 9600 baudrate
    localparam countMax = 2; // for testing 
    reg [25:0] count = 0;
    parameter S0 = 4'd0, S1 = 4'd1, S2 = 4'd2, S3 = 4'd3, S4 = 4'd4, S5 = 4'd5, S6 = 4'd6, S7 = 4'd7, S8 = 4'd8, S9 = 4'd9, S10 = 4'd10;
    reg [3:0] currentState;
    reg [3:0] nextState;
    reg sync1, sync2;
    reg [7:0] data_reg;

    //= state transistion =//
    always @(*)begin
        case(currentState)
            S0: begin
                if(sync2)
                    nextState = S1;
                else
                    nextState = S0;
            end
            S1: begin
                if(sync2)
                    nextState = S1;
                else
                    nextState = S2;
            end
            S2: begin
                nextState = S3;
            end
            S3: begin
                nextState = S4;
            end
            S4: begin
                nextState = S5;
            end
            S5: begin
                nextState = S6;
            end
            S6: begin
                nextState = S7;
            end
            S7: begin             
                nextState = S8;
            end
            S8: begin
                nextState = S9;
            end
            S9: begin
                nextState = S10;
            end
            S10: begin
                if(sync2)
                    nextState = S1;
                else
                    nextState = S0;
            end
            default: nextState = S0;
        endcase
    end

    //= output update =//
    always @(posedge clk_100mhz or posedge rst)begin
        sync1 <= rx_line;
        sync2 <= sync1;
        if(rst) begin
            currentState <= S0;
            data <= 8'b0000_0000;
        end else if (count < countMax) begin
            // if(currentState == S1 && count == countMax/2) begin
            //     count <= 0;
            //     currentState <= nextState;
            // end else
                count <= count + 1;
        end else begin
            count <= 0;
            currentState <= nextState;
            case(currentState)
                S0: data_reg <= 8'b0000_0000;
                S1: data_reg <= 8'b0000_0000;
                S2: data_reg[0] <= sync2;
                S3: data_reg[1] <= sync2;
                S4: data_reg[2] <= sync2;
                S5: data_reg[3] <= sync2;
                S6: data_reg[4] <= sync2;
                S7: data_reg[5] <= sync2;
                S8: data_reg[6] <= sync2;
                S9: data_reg[7] <= sync2;
                S10: begin
                    if(nextState == S1) // if next state is S1, it means stop bit is correct, we can update data
                        data <= {sync2,data_reg};
                    else
                        data <= 8'b0000_0000; // if stop bit is wrong, reset data to 0
                end
                default: data_reg <= 8'b0000_0000;
            endcase
        end
    end

endmodule

lab2/testbench/rx_tb.v
`timescale 1ns / 1ps

module rx_tb();

reg clk;
reg rst;
reg rx_line;
wire [7:0] data;

reg correct;
integer testNum;

reg [7:0] d;
reg [9:0] d_10; // for testing 10 bit frame
integer i;

// Instantiate RX
rx my_rx (
    .clk_100mhz(clk),
    .rst(rst),
    .rx_line(rx_line),
    .data(data)
);

// Clock
always begin
    #0.5 clk = ~clk;
end

initial begin
    $dumpfile("rx_wave.vcd");
    $dumpvars(0, rx_tb);
    clk = 0;
    rst = 0;
    rx_line = 1; 
    correct = 1;

    //= reset check =//
    testNum = 1;
    #3;
    rst = 1;
    #3;
    rst = 0;

    if (data != 8'b00000000) correct = 0;

    //= receive byte =//
    testNum = 2;
    d = 8'b11001100;
    #3;
    // Start bit
    rx_line = 0;
    #3;
    // Data bits
    for (i = 0; i < 8; i = i + 1) begin
        rx_line = d[i];
        #3;
    end
    // Stop bit
    rx_line = 1;
    #3;

    if (data != d) correct = 0;
    #3;
    correct = 1;

    //== 2nd recieve, to make sure that data will overwrite ==//
    testNum = 3;
    d = 8'b01010101;
    #3;
    // Start bit
    rx_line = 0;
    #3;
    // Data bits
    for (i = 0; i < 8; i = i + 1) begin
        rx_line = d[i];
        #3;
    end
    // Stop bit
    rx_line = 1;
    #3;

    if (data != d) correct = 0;
    #3;
    correct = 1;
    

    //= receive 10 bit frame, make sure only the first =//
    testNum = 4;
    d = 8'b10111010;
    d_10 = {2'b11,d}; // add 2 more bits at the end, should be ignored
    #3;
    // Start bit
    rx_line = 0;
    #3;
    // Data bits
    for (i = 0; i < 10; i = i + 1) begin
        rx_line = d_10[i];
        #3;
    end
    // Stop bit
    rx_line = 1;
    #3;

    if (data != d) correct = 0;
    #3;
    correct = 1;

    //= reset mid receiving =//
    testNum = 5;
    d = 8'b11111111;
    #3;
    // Start bit
    rx_line = 0;
    #3;
    // Data bits
    for (i = 0; i < 3; i = i + 1) begin
        rx_line = d[i];
        #3;
    end
    rst = 1; // reset in the middle of transmission, should reset everything
    for (i = 3; i < 8; i = i + 1) begin
        rx_line = d[i];
        #3;
        rst = 0;
    end
    // Stop bit
    rx_line = 1;
    #3;

    if (data != 8'b00000000) correct = 0;
    #3;
    correct = 1;


    //== no stop bit ==//
    testNum = 6;
    d = 8'b01010101;
    #3;
    // Start bit
    rx_line = 0;
    #3;
    // Data bits
    for (i = 0; i < 8; i = i + 1) begin
        rx_line = d[i];
        #3;
    end
    // Stop bit
    // rx_line = 1;
    #3;

    if (data != 8'b00000000) correct = 0;
    #3;
    correct = 1;

    // Finish
    #5;
    $stop;
end

endmodule

lab2/rx_wave.vcd
$date
	Fri Apr 10 12:14:47 2026
$end
$version
	Icarus Verilog
$end
$timescale
	1ps
$end
$scope module rx_tb $end
$var wire 8 ! data [7:0] $end
$var reg 1 " clk $end
$var reg 1 # correct $end
$var reg 8 $ d [7:0] $end
$var reg 10 % d_10 [9:0] $end
$var reg 1 & rst $end
$var reg 1 ' rx_line $end
$var integer 32 ( i [31:0] $end
$var integer 32 ) testNum [31:0] $end
$scope module my_rx $end
$var wire 1 " clk_100mhz $end
$var wire 1 & rst $end
$var wire 1 ' rx_line $end
$var parameter 4 * S0 $end
$var parameter 4 + S1 $end
$var parameter 4 , S10 $end
$var parameter 4 - S2 $end
$var parameter 4 . S3 $end
$var parameter 4 / S4 $end
$var parameter 4 0 S5 $end
$var parameter 4 1 S6 $end
$var parameter 4 2 S7 $end
$var parameter 4 3 S8 $end
$var parameter 4 4 S9 $end
$var parameter 32 5 countMax $end
$var reg 26 6 count [25:0] $end
$var reg 4 7 currentState [3:0] $end
$var reg 8 8 data [7:0] $end
$var reg 8 9 data_reg [7:0] $end
$var reg 4 : nextState [3:0] $end
$var reg 1 ; sync1 $end
$var reg 1 < sync2 $end
$upscope $end
$upscope $end
$enddefinitions $end
$comment Show the parameter values. $end
$dumpall
b10 5
b1001 4
b1000 3
b111 2
b110 1
b101 0
b100 /
b11 .
b10 -
b1010 ,
b1 +
b0 *
$end
#0
$dumpvars
x<
x;
bx :
bx 9
bx 8
bx 7
b0 6
b1 )
bx (
1'
0&
bx %
bx $
1#
0"
bx !
$end
#500
b1 6
1;
1"
#1000
0"
#1500
b0 :
b10 6
1<
1"
#2000
0"
#2500
b1 :
b0 9
b0 7
b0 6
1"
#3000
b0 !
b0 8
0"
1&
#3500
1"
#4000
0"
#4500
1"
#5000
0"
#5500
1"
#6000
0"
b11001100 $
b10 )
0&
#6500
b1 6
1"
#7000
0"
#7500
b10 6
1"
#8000
0"
#8500
b1 7
b0 6
1"
#9000
0"
0'
#9500
b1 6
0;
1"
#10000
0"
#10500
b10 :
b10 6
0<
1"
#11000
0"
#11500
b11 :
b10 7
b0 6
1"
#12000
0"
b0 (
#12500
b1 6
1"
#13000
0"
#13500
b10 6
1"
#14000
0"
#14500
b100 :
b11 7
b0 6
1"
#15000
0"
b1 (
#15500
b1 6
1"
#16000
0"
#16500
b10 6
1"
#17000
0"
#17500
b101 :
b100 7
b0 6
1"
#18000
0"
1'
b10 (
#18500
b1 6
1;
1"
#19000
0"
#19500
b10 6
1<
1"
#20000
0"
#20500
b110 :
b100 9
b101 7
b0 6
1"
#21000
0"
b11 (
#21500
b1 6
1"
#22000
0"
#22500
b10 6
1"
#23000
0"
#23500
b111 :
b1100 9
b110 7
b0 6
1"
#24000
0"
0'
b100 (
#24500
b1 6
0;
1"
#25000
0"
#25500
b10 6
0<
1"
#26000
0"
#26500
b1000 :
b111 7
b0 6
1"
#27000
0"
b101 (
#27500
b1 6
1"
#28000
0"
#28500
b10 6
1"
#29000
0"
#29500
b1001 :
b1000 7
b0 6
1"
#30000
0"
1'
b110 (
#30500
b1 6
1;
1"
#31000
0"
#31500
b10 6
1<
1"
#32000
0"
#32500
b1010 :
b1001100 9
b1001 7
b0 6
1"
#33000
0"
b111 (
#33500
b1 6
1"
#34000
0"
#34500
b10 6
1"
#35000
0"
#35500
b1 :
b11001100 9
b1010 7
b0 6
1"
#36000
0"
b1000 (
#36500
b1 6
1"
#37000
0"
#37500
b10 6
1"
#38000
0"
#38500
b11001100 !
b11001100 8
b1 7
b0 6
1"
#39000
0"
#39500
b1 6
1"
#40000
0"
#40500
b10 6
1"
#41000
0"
#41500
b0 9
b0 6
1"
#42000
0"
b1010101 $
b11 )
#42500
b1 6
1"
#43000
0"
#43500
b10 6
1"
#44000
0"
#44500
b0 6
1"
#45000
0"
0'
#45500
b1 6
0;
1"
#46000
0"
#46500
b10 :
b10 6
0<
1"
#47000
0"
#47500
b11 :
b10 7
b0 6
1"
#48000
0"
1'
b0 (
#48500
b1 6
1;
1"
#49000
0"
#49500
b10 6
1<
1"
#50000
0"
#50500
b100 :
b1 9
b11 7
b0 6
1"
#51000
0"
0'
b1 (
#51500
b1 6
0;
1"
#52000
0"
#52500
b10 6
0<
1"
#53000
0"
#53500
b101 :
b100 7
b0 6
1"
#54000
0"
1'
b10 (
#54500
b1 6
1;
1"
#55000
0"
#55500
b10 6
1<
1"
#56000
0"
#56500
b110 :
b101 9
b101 7
b0 6
1"
#57000
0"
0'
b11 (
#57500
b1 6
0;
1"
#58000
0"
#58500
b10 6
0<
1"
#59000
0"
#59500
b111 :
b110 7
b0 6
1"
#60000
0"
1'
b100 (
#60500
b1 6
1;
1"
#61000
0"
#61500
b10 6
1<
1"
#62000
0"
#62500
b1000 :
b10101 9
b111 7
b0 6
1"
#63000
0"
0'
b101 (
#63500
b1 6
0;
1"
#64000
0"
#64500
b10 6
0<
1"
#65000
0"
#65500
b1001 :
b1000 7
b0 6
1"
#66000
0"
1'
b110 (
#66500
b1 6
1;
1"
#67000
0"
#67500
b10 6
1<
1"
#68000
0"
#68500
b1010 :
b1010101 9
b1001 7
b0 6
1"
#69000
0"
0'
b111 (
#69500
b1 6
0;
1"
#70000
0"
#70500
b10 6
0<
1"
#71000
0"
#71500
b0 :
b1010 7
b0 6
1"
#72000
0"
1'
b1000 (
#72500
b1 6
1;
1"
#73000
0"
#73500
b1 :
b10 6
1<
1"
#74000
0"
#74500
b1010101 !
b1010101 8
b1 7
b0 6
1"
#75000
0"
#75500
b1 6
1"
#76000
0"
#76500
b10 6
1"
#77000
0"
#77500
b0 9
b0 6
1"
#78000
0"
b1110111010 %
b10111010 $
b100 )
#78500
b1 6
1"
#79000
0"
#79500
b10 6
1"
#80000
0"
#80500
b0 6
1"
#81000
0"
0'
#81500
b1 6
0;
1"
#82000
0"
#82500
b10 :
b10 6
0<
1"
#83000
0"
#83500
b11 :
b10 7
b0 6
1"
#84000
0"
b0 (
#84500
b1 6
1"
#85000
0"
#85500
b10 6
1"
#86000
0"
#86500
b100 :
b11 7
b0 6
1"
#87000
0"
1'
b1 (
#87500
b1 6
1;
1"
#88000
0"
#88500
b10 6
1<
1"
#89000
0"
#89500
b101 :
b10 9
b100 7
b0 6
1"
#90000
0"
0'
b10 (
#90500
b1 6
0;
1"
#91000
0"
#91500
b10 6
0<
1"
#92000
0"
#92500
b110 :
b101 7
b0 6
1"
#93000
0"
1'
b11 (
#93500
b1 6
1;
1"
#94000
0"
#94500
b10 6
1<
1"
#95000
0"
#95500
b111 :
b1010 9
b110 7
b0 6
1"
#96000
0"
b100 (
#96500
b1 6
1"
#97000
0"
#97500
b10 6
1"
#98000
0"
#98500
b1000 :
b11010 9
b111 7
b0 6
1"
#99000
0"
b101 (
#99500
b1 6
1"
#100000
0"
#100500
b10 6
1"
#101000
0"
#101500
b1001 :
b111010 9
b1000 7
b0 6
1"
#102000
0"
0'
b110 (
#102500
b1 6
0;
1"
#103000
0"
#103500
b10 6
0<
1"
#104000
0"
#104500
b1010 :
b1001 7
b0 6
1"
#105000
0"
1'
b111 (
#105500
b1 6
1;
1"
#106000
0"
#106500
b10 6
1<
1"
#107000
0"
#107500
b1 :
b10111010 9
b1010 7
b0 6
1"
#108000
0"
b1000 (
#108500
b1 6
1"
#109000
0"
#109500
b10 6
1"
#110000
0"
#110500
b10111010 !
b10111010 8
b1 7
b0 6
1"
#111000
0"
b1001 (
#111500
b1 6
1"
#112000
0"
#112500
b10 6
1"
#113000
0"
#113500
b0 9
b0 6
1"
#114000
0"
b1010 (
#114500
b1 6
1"
#115000
0"
#115500
b10 6
1"
#116000
0"
#116500
b0 6
1"
#117000
0"
#117500
b1 6
1"
#118000
0"
#118500
b10 6
1"
#119000
0"
#119500
b0 6
1"
#120000
0"
b11111111 $
b101 )
#120500
b1 6
1"
#121000
0"
#121500
b10 6
1"
#122000
0"
#122500
b0 6
1"
#123000
0"
0'
#123500
b1 6
0;
1"
#124000
0"
#124500
b10 :
b10 6
0<
1"
#125000
0"
#125500
b11 :
b10 7
b0 6
1"
#126000
0"
1'
b0 (
#126500
b1 6
1;
1"
#127000
0"
#127500
b10 6
1<
1"
#128000
0"
#128500
b100 :
b1 9
b11 7
b0 6
1"
#129000
0"
b1 (
#129500
b1 6
1"
#130000
0"
#130500
b10 6
1"
#131000
0"
#131500
b101 :
b11 9
b100 7
b0 6
1"
#132000
0"
b10 (
#132500
b1 6
1"
#133000
0"
#133500
b10 6
1"
#134000
0"
#134500
b110 :
b111 9
b101 7
b0 6
1"
#135000
b1 :
b0 !
b0 8
b0 7
0"
1&
b11 (
#135500
1"
#136000
0"
#136500
1"
#137000
0"
#137500
1"
#138000
0"
b100 (
0&
#138500
b1 6
1"
#139000
0"
#139500
b10 6
1"
#140000
0"
#140500
b0 9
b1 7
b0 6
1"
#141000
0"
b101 (
#141500
b1 6
1"
#142000
0"
#142500
b10 6
1"
#143000
0"
#143500
b0 6
1"
#144000
0"
b110 (
#144500
b1 6
1"
#145000
0"
#145500
b10 6
1"
#146000
0"
#146500
b0 6
1"
#147000
0"
b111 (
#147500
b1 6
1"
#148000
0"
#148500
b10 6
1"
#149000
0"
#149500
b0 6
1"
#150000
0"
b1000 (
#150500
b1 6
1"
#151000
0"
#151500
b10 6
1"
#152000
0"
#152500
b0 6
1"
#153000
0"
#153500
b1 6
1"
#154000
0"
#154500
b10 6
1"
#155000
0"
#155500
b0 6
1"
#156000
0"
b1010101 $
b11 )
#156500
b1 6
1"
#157000
0"
#157500
b10 6
1"
#158000
0"
#158500
b0 6
1"
#159000
0"
0'
#159500
b1 6
0;
1"
#160000
0"
#160500
b10 :
b10 6
0<
1"
#161000
0"
#161500
b11 :
b10 7
b0 6
1"
#162000
0"
1'
b0 (
#162500
b1 6
1;
1"
#163000
0"
#163500
b10 6
1<
1"
#164000
0"
#164500
b100 :
b1 9
b11 7
b0 6
1"
#165000
0"
0'
b1 (
#165500
b1 6
0;
1"
#166000
0"
#166500
b10 6
0<
1"
#167000
0"
#167500
b101 :
b100 7
b0 6
1"
#168000
0"
1'
b10 (
#168500
b1 6
1;
1"
#169000
0"
#169500
b10 6
1<
1"
#170000
0"
#170500
b110 :
b101 9
b101 7
b0 6
1"
#171000
0"
0'
b11 (
#171500
b1 6
0;
1"
#172000
0"
#172500
b10 6
0<
1"
#173000
0"
#173500
b111 :
b110 7
b0 6
1"
#174000
0"
1'
b100 (
#174500
b1 6
1;
1"
#175000
0"
#175500
b10 6
1<
1"
#176000
0"
#176500
b1000 :
b10101 9
b111 7
b0 6
1"
#177000
0"
0'
b101 (
#177500
b1 6
0;
1"
#178000
0"
#178500
b10 6
0<
1"
#179000
0"
#179500
b1001 :
b1000 7
b0 6
1"
#180000
0"
1'
b110 (
#180500
b1 6
1;
1"
#181000
0"
#181500
b10 6
1<
1"
#182000
0"
#182500
b1010 :
b1010101 9
b1001 7
b0 6
1"
#183000
0"
0'
b111 (
#183500
b1 6
0;
1"
#184000
0"
#184500
b10 6
0<
1"
#185000
0"
#185500
b0 :
b1010 7
b0 6
1"
#186000
0"
b1000 (
#186500
b1 6
1"
#187000
0"
#187500
b10 6
1"
#188000
0"
#188500
b0 7
b0 6
1"
#189000
0"
#189500
b1 6
1"
#190000
0"
#190500
b10 6
1"
#191000
0"
#191500
b0 9
b0 6
1"
#192000
0"
#192500
b1 6
1"
#193000
0"
#193500
b10 6
1"
#194000
0"
#194500
b0 6
1"
#195000
0"
#195500
b1 6
1"
#196000
0"
#196500
b10 6
1"
